{
    "musicas":[
        {
            "id": 1,
            "nome": "one",
            "autor": "metallica",
            "genero": "rock",
            "ano": 2003
        },
        {
            "id": 2,
            "nome": "nothing else matters",
            "autor": "metallica",
            "genero": "rock",
            "ano": 2005
        },
        {
            "id": 3,
            "nome": "enter sandman",
            "autor": "metallica",
            "genero": "rock",
            "ano": 2007
        }
    ]
}